printj/__init__.py
printj/lib.py
printj/printj_colors.py
printj-0.1.1.dist-info/LICENSE
printj-0.1.1.dist-info/METADATA
printj-0.1.1.dist-info/WHEEL
printj-0.1.1.dist-info/top_level.txt
printj-0.1.1.dist-info/RECORD
