Metadata-Version: 2.1
Name: printj
Version: 0.1.1
Summary: Print log info and color text, speak text and helps debugging
Home-page: https://github.com/Jitesh17/printj
Author: Jitesh Gosar
Author-email: gosar95@gmail.com
Classifier: Programming Language :: Python :: 3
Classifier: Programming Language :: Python :: 3.5
Classifier: Programming Language :: Python :: 3.6
Classifier: Programming Language :: Python :: 3.7
Classifier: License :: OSI Approved :: MIT License
Classifier: Operating System :: OS Independent
Requires-Python: >=3.6
License-File: LICENSE
